[{"contenidos":[{"id":"Q6M0F8A9N2","titulo":"Viaje a zacapu","descripcion":"Viaje a los campos de agave","idCreador":"0nB0lnHR17","visualizaciones":[],"likes":[],"comentarios":[],"donaciones":0.0,"imagePath":"imagenes/Viaje a zacapu.jpg"},{"id":"R7E9C7Q0P5","titulo":"Viaje con mezcaleras","descripcion":"Viaje con la asociacion de mezcaleras de michoacan a conocer zacapu y sus vinedos","idCreador":"0nB0lnHR17","visualizaciones":[],"likes":[],"comentarios":[],"donaciones":0.0,"imagePath":"imagenes/Viaje con mezcaleras.jpg"}],"cuentaBloqueada":false,"suscriptores":["K5pPWlhTYd"],"partner":true,"id":"0nB0lnHR17","nombre":"Mario","correo":"mario@gmail.com","contrasena":"addb47291ee169f330801ce73520b96f2eaf20ea"}]